neon/__init__.py
neon/data_structures.py
neon/features/__init__.py
neon/features/cyclical.py
neon/features/swem.py
neon_ml-0.1.0.dist-info/WHEEL
neon_ml-0.1.0.dist-info/METADATA
neon_ml-0.1.0.dist-info/RECORD
